{
  "type": "minecraft:crafting_shapeless",
  "category": "building",
  "ingredients": [
    {
      "item": "flavored:cauliflower_curd"
    },
    {
      "item": "flavored:cauliflower_curd"
    },
    {
      "item": "flavored:cauliflower_curd"
    },
    {
      "item": "flavored:cauliflower_curd"
    },
    {
      "item": "flavored:cauliflower_curd"
    },
    {
      "item": "flavored:cauliflower_curd"
    },
    {
      "item": "flavored:cauliflower_curd"
    },
    {
      "item": "flavored:cauliflower_curd"
    },
    {
      "item": "flavored:cauliflower_curd"
    }
  ],
  "result": {
    "count": 1,
    "id": "flavored:cauliflower"
  }
}